{
  "last_updated": "2026-04-04",
  "currency": "CHF",
  "cash_balance": 620.73,
  "deposited_capital": 7500.00,
  "positions": [
    {
      "ticker_swissquote": "AUCHAH",
      "isin": "CH0106027128",
      "valor": 10602712,
      "name": "UBS ETF (CH) Gold hedged CHF",
      "type": "ETF",
      "exchange": "SWX",
      "quantity": 20,
      "average_buy_price": 165.72,
      "effective_buy_price": 166.44,
      "buy_date": "2026-02-20",
      "total_cost": 3314.40,
      "fees": 14.34,
      "total_cost_with_fees": 3328.74,
      "current_price": 153.56,
      "price_currency": "CHF",
      "price_source": "https://www.cash.ch/fonds/ubs-etf-ch-ubs-gold-hchf-etf-10602712/swx/chf",
      "notes": "ETF or couvert CHF. Cours 153.56 CHF (cloture SIX 02/04, derniere seance avant Paques). Variation -1.75% vs cloture precedente 156.30."
    },
    {
      "ticker_swissquote": "FIVETQ",
      "isin": "CH0467720410",
      "valor": 46772041,
      "name": "Swissquote 5G Revolution Index (Leonteq Tracker)",
      "type": "structured_product",
      "exchange": "QMH",
      "quantity": 19,
      "average_buy_price": 256.84,
      "effective_buy_price": 257.56,
      "buy_date": "2026-02-18",
      "total_cost_usd": 4879.96,
      "fees_usd": 13.70,
      "total_cost_with_fees_usd": 4893.66,
      "total_cost_chf": 3814.97,
      "usdchf_at_purchase": 0.7796,
      "current_price": 249.99,
      "price_currency": "USD",
      "price_source": "https://www.cash.ch/derivate/leoz-open-46772041/qmh/usd",
      "notes": "Produit structure Leonteq. Cote en USD. Cours 249.99 USD (cloture 02/04). Correction vs rapport 03/04 qui indiquait 246.46 (prix indicatif Swissquote perime). Variation +1.43% vs cloture 01/04 (246.46). USD/CHF 0.8000."
    }
  ],
  "transactions": [
    {
      "date": "2026-02-20",
      "type": "buy",
      "ticker": "AUCHAH",
      "quantity": 20,
      "price": 165.72,
      "currency": "CHF",
      "fees": 14.34,
      "total": 3314.40,
      "total_with_fees": 3328.74
    },
    {
      "date": "2026-02-18",
      "type": "buy",
      "ticker": "FIVETQ",
      "quantity": 19,
      "price": 256.84,
      "currency": "USD",
      "fees_usd": 13.70,
      "total_usd": 4879.96,
      "total_with_fees_usd": 4893.66,
      "total_chf": 3814.97,
      "usdchf_at_purchase": 0.7796
    }
  ],
  "performance": {
    "deposited_capital": 7500.00,
    "current_value": 7491.78,
    "total_return_pct": -0.11
  }
}
